{
    "schemaVersion": 1,
    "metadata": {
        "plugin": "minitabs",
        "version": "1.0.0",
        "title": "Minitabs",
        "description": "Minitabs Localization & Tweaks",
        "language": "zh-cn",
        "supportedVersions": "0.0.12",
        "author": ""
    },
    "dict": {
        "main.js": {
            "ast": [
                {
                    "type": "AssignmentExpression",
                    "name": "innerText",
                    "source": "⚠️ 检测到自引用，已阻止渲染",
                    "target": "⚠️ 检测到自引用，已阻止渲染"
                },
                {
                    "type": "NewExpression",
                    "name": "Notice",
                    "source": "copy！",
                    "target": "复制！"
                },
                {
                    "type": "NewExpression",
                    "name": "Notice",
                    "source": "err: copy",
                    "target": "错误：复制"
                },
                {
                    "type": "ObjectProperty",
                    "name": "text",
                    "source": "更多知识管理访问 Obsidian 中文网：https://Obsidian.vip",
                    "target": "更多知识管理访问 Obsidian 中文网：https://Obsidian.vip"
                },
                {
                    "type": "ObjectProperty",
                    "name": "text",
                    "source": "使用方法：复制代码块到你的笔记页面。",
                    "target": "使用方法：复制代码块到你的笔记页面。"
                },
                {
                    "type": "ObjectProperty",
                    "name": "text",
                    "source": "tabs一共四种分割线分别是 ===、--- 、~~~ 和 @@@ 。",
                    "target": "tabs一共四种分割线分别是 ===、--- 、~~~ 和 @@@ 。"
                },
                {
                    "type": "ObjectProperty",
                    "name": "text",
                    "source": "可以根据不同的分割线使相互嵌套tabs",
                    "target": "可以根据不同的分割线使相互嵌套tabs"
                },
                {
                    "type": "ObjectProperty",
                    "name": "text",
                    "source": "按钮在上面 ↑",
                    "target": "按钮在上面 ↑"
                },
                {
                    "type": "ObjectProperty",
                    "name": "text",
                    "source": "````minitabs\n//按钮在上面\ntabs\n`按钮1` `按钮2` `可以一直写下去……` \n===\n第一个按钮对应的页面\n===\n按钮二对应的页面\n===\n按钮三对应的页面\n````",
                    "target": "````minitabs\n//按钮在上面\ntabs\n`按钮1` `按钮2` `可以一直写下去……` \n===\n第一个按钮对应的页面\n===\n按钮二对应的页面\n===\n按钮三对应的页面\n````"
                },
                {
                    "type": "ObjectProperty",
                    "name": "text",
                    "source": "按钮在下面 ↓",
                    "target": "按钮在下面 ↓"
                },
                {
                    "type": "ObjectProperty",
                    "name": "text",
                    "source": "````minitabs\n//按钮在下面\ntabsBottom\n`按钮1` `按钮2` `可以一直写下去……` \n===\n第一个按钮对应的页面\n===\n按钮二对应的页面\n===\n按钮三对应的页面\n````",
                    "target": "````minitabs\n//按钮在下面\ntabsBottom\n`按钮1` `按钮2` `可以一直写下去……` \n===\n第一个按钮对应的页面\n===\n按钮二对应的页面\n===\n按钮三对应的页面\n````"
                },
                {
                    "type": "ObjectProperty",
                    "name": "text",
                    "source": "四象限",
                    "target": "四象限"
                },
                {
                    "type": "ObjectProperty",
                    "name": "text",
                    "source": "````minitabs\nfourQuadrant\n---\n### 不紧急但重要⭐⭐⭐\n- [ ] 呆呆\n---\n### 紧急且重要⭐⭐⭐⭐\n- [ ] 呆呆\n---\n### 不紧急不重要⭐\n- [ ] 呆呆\n---\n### 紧急不重要⭐⭐\n- [ ] 呆呆\n````",
                    "target": "````minitabs\nfourQuadrant\n---\n### 不紧急但重要⭐⭐⭐\n- [ ] 呆呆\n---\n### 紧急且重要⭐⭐⭐⭐\n- [ ] 呆呆\n---\n### 不紧急不重要⭐\n- [ ] 呆呆\n---\n### 紧急不重要⭐⭐\n- [ ] 呆呆\n````"
                },
                {
                    "type": "ObjectProperty",
                    "name": "text",
                    "source": "访问此插件的GitHub仓库：https://github.com/ssjy1919/Obsidian-minitabs",
                    "target": "访问此插件的GitHub仓库：https://github.com/ssjy1919/Obsidian-minitabs"
                }
            ],
            "regex": []
        }
    }
}